agentlys/__init__.py
agentlys/base.py
agentlys/chat.py
agentlys/mcp.py
agentlys/model.py
agentlys/utils.py
agentlys/providers/anthropic.py
agentlys/providers/base_provider.py
agentlys/providers/default.py
agentlys/providers/openai.py
agentlys/providers/openai_function_legacy.py
agentlys/providers/openai_function_shim.py
agentlys/providers/utils.py
agentlys-1.4.1.dist-info/licenses/LICENSE
agentlys-1.4.1.dist-info/METADATA
agentlys-1.4.1.dist-info/WHEEL
agentlys-1.4.1.dist-info/top_level.txt
agentlys-1.4.1.dist-info/RECORD
