Metadata-Version: 2.4
Name: agentlys
Version: 1.4.1
Summary: Lightweight AI agent library. Turn Python functions/classes into AI tools instantly.
Author-email: Benjamin Derville <benderville@gmail.com>
License: MIT License
Project-URL: Repository, https://github.com/myriade-ai/agentlys
Project-URL: Changelog, https://github.com/myriade-ai/agentlys/blob/master/CHANGELOG.md
Requires-Python: >=3.9
License-File: LICENSE
Requires-Dist: pillow==11.3.0
Requires-Dist: pydantic==2.12.5
Provides-Extra: anthropic
Requires-Dist: anthropic>=0.46.0; extra == "anthropic"
Provides-Extra: openai
Requires-Dist: openai>=1.63.2; extra == "openai"
Provides-Extra: mcp
Requires-Dist: mcp>=1.6.0; python_version >= "3.10" and extra == "mcp"
Provides-Extra: all
Requires-Dist: anthropic>=0.46.0; extra == "all"
Requires-Dist: openai>=1.63.2; extra == "all"
Requires-Dist: mcp>=1.6.0; python_version >= "3.10" and extra == "all"
Provides-Extra: build
Requires-Dist: uv~=0.9.5; extra == "build"
Dynamic: license-file
